fast_test_database/__init__.py
fast_test_database-0.2.23.dist-info/METADATA
fast_test_database-0.2.23.dist-info/WHEEL
fast_test_database-0.2.23.dist-info/RECORD
