Metadata-Version: 2.4
Name: fast-test-database
Version: 0.2.23
Summary: Configure an in-memory database for running Django tests
License: GPL-3.0-or-later
Author: Alexey Kotlyarov
Author-email: a@koterpillar.com
Requires-Python: >=3.11,<4.0
Classifier: License :: OSI Approved :: GNU General Public License v3 or later (GPLv3+)
Classifier: Programming Language :: Python :: 3
Classifier: Programming Language :: Python :: 3.11
Classifier: Programming Language :: Python :: 3.12
Classifier: Programming Language :: Python :: 3.13
Classifier: Programming Language :: Python :: 3.14
Requires-Dist: Django (>=5.2.8,<6.0.0)
